material_palette_generator/__init__.py
material_palette_generator/cli.py
material_palettes_generator-1.2.1.dist-info/licenses/LICENSE
material_palettes_generator-1.2.1.dist-info/METADATA
material_palettes_generator-1.2.1.dist-info/WHEEL
material_palettes_generator-1.2.1.dist-info/entry_points.txt
material_palettes_generator-1.2.1.dist-info/top_level.txt
material_palettes_generator-1.2.1.dist-info/RECORD
