Metadata-Version: 2.4
Name: material-palettes-generator
Version: 1.2.1
Summary: Generate Material Design color palettes in Python
Author-email: Black Steel <unknown.user2135@proton.me>
License: MIT
Project-URL: Homepage, https://github.com/blacksteel3/material-palette-generator
Project-URL: Documentation, https://github.com/blacksteel3/material-palette-generator#readme
Project-URL: Bug Tracker, https://github.com/blacksteel3/material-palette-generator/issues
Keywords: material design,color palette,color generator,theming
Classifier: Development Status :: 5 - Production/Stable
Classifier: Intended Audience :: Developers
Classifier: Intended Audience :: End Users/Desktop
Classifier: Topic :: Software Development :: User Interfaces
Classifier: Topic :: Multimedia :: Graphics
Classifier: Topic :: Artistic Software
Classifier: License :: OSI Approved :: MIT License
Classifier: Programming Language :: Python
Classifier: Programming Language :: Python :: 3
Classifier: Programming Language :: Python :: 3.6
Classifier: Programming Language :: Python :: 3.7
Classifier: Programming Language :: Python :: 3.8
Classifier: Programming Language :: Python :: 3.9
Classifier: Programming Language :: Python :: 3.10
Classifier: Programming Language :: Python :: 3.11
Classifier: Programming Language :: Python :: 3.12
Classifier: Environment :: Console
Classifier: Operating System :: OS Independent
Requires-Python: >=3.6
License-File: LICENSE
Dynamic: license-file
